{
    "status":"ok",
    "knowledge":[
        "文件系统"
    ],
    "degree_of_difficulty":1,
    "explain":"    ```\n    解：扇区总数：1010016＝16000\n          则位示图的位数：16000/8＝2000字节\n          位示图中空闲块数：216>16000  所以要用2字节存储\n         则位示图的大小为：2000+0＝2002字节\n    空闲文件目录的每条记录占用5个字节\n    2002字节可以存放的表目数为：2002/5＝400\n    当空闲文件目录数为400时，空闲文件目录大于位示图\n    ```\n\n",
    "question":"有一磁盘组共有10个盘面，每个盘面上有100个磁道，每个磁道有16个扇区。假定分配以扇区为单位，若使用位示图管理磁盘空间，问位示图需要占用多少空间？若空闲文\n件目录的每条记录占用5个字节，问什么时候空闲文件目录大于位示图？\n",
    "source":"网络",
    "answer":"    ```\n    解：扇区总数：1010016＝16000\n          则位示图的位数：16000/8＝2000字节\n          位示图中空闲块数：216>16000  所以要用2字节存储\n         则位示图的大小为：2000+0＝2002字节\n    空闲文件目录的每条记录占用5个字节\n    2002字节可以存放的表目数为：2002/5＝400\n    当空闲文件目录数为400时，空闲文件目录大于位示图\n    ```\n\n",
    "type":"question_answer",
    "q_number":1084
}